MIMDE/LLM_toolkit.py
MIMDE/__init__.py
MIMDE/cost.py
MIMDE/data_cleaner.py
MIMDE/output_summaries.py
MIMDE/pydantic_classes.py
MIMDE/response_mapping.py
MIMDE/theme_extraction.py
MIMDE/config/model_configs.yaml
MIMDE-1.1.2.dist-info/LICENSE
MIMDE-1.1.2.dist-info/METADATA
MIMDE-1.1.2.dist-info/WHEEL
MIMDE-1.1.2.dist-info/top_level.txt
MIMDE-1.1.2.dist-info/RECORD
